schedulifyx/__init__.py
schedulifyx/client.py
schedulifyx/types.py
schedulifyx-1.0.5.dist-info/METADATA
schedulifyx-1.0.5.dist-info/WHEEL
schedulifyx-1.0.5.dist-info/top_level.txt
schedulifyx-1.0.5.dist-info/RECORD
