Metadata-Version: 2.4
Name: schedulifyx
Version: 1.0.5
Summary: Official Python SDK for SchedulifyX API - Social media scheduling made easy
Author-email: SchedulifyX <support@schedulifyx.com>
License-Expression: MIT
Project-URL: Homepage, https://app.schedulifyx.com
Project-URL: Documentation, https://app.schedulifyx.com/docs/
Project-URL: Repository, https://github.com/Eh-Mr-SK/schedulifyx-sdk-python
Project-URL: Issues, https://github.com/Eh-Mr-SK/schedulifyx-sdk-python/issues
Keywords: schedulify,schedulifyx,social-media,scheduling,api,sdk,instagram,twitter,facebook,linkedin,tiktok
Classifier: Development Status :: 5 - Production/Stable
Classifier: Intended Audience :: Developers
Classifier: Operating System :: OS Independent
Classifier: Programming Language :: Python :: 3
Classifier: Programming Language :: Python :: 3.8
Classifier: Programming Language :: Python :: 3.9
Classifier: Programming Language :: Python :: 3.10
Classifier: Programming Language :: Python :: 3.11
Classifier: Programming Language :: Python :: 3.12
Classifier: Topic :: Internet :: WWW/HTTP
Classifier: Topic :: Software Development :: Libraries :: Python Modules
Requires-Python: >=3.8
Requires-Dist: requests>=2.25.0
Provides-Extra: dev
Requires-Dist: pytest>=7.0.0; extra == "dev"
Requires-Dist: pytest-cov>=4.0.0; extra == "dev"
Requires-Dist: responses>=0.23.0; extra == "dev"
